bensgaming/__init__.py
bensgaming/main.py
bensgaming-1.0.0.dist-info/METADATA
bensgaming-1.0.0.dist-info/WHEEL
bensgaming-1.0.0.dist-info/entry_points.txt
bensgaming-1.0.0.dist-info/top_level.txt
bensgaming-1.0.0.dist-info/RECORD
