Metadata-Version: 2.4
Name: bensgaming
Version: 1.0.0
Summary: BensGamingOnTop.
Author: BensGaming
Requires-Python: >=3.7
Requires-Dist: numpy
Requires-Dist: requests
Requires-Dist: discord.py
Requires-Dist: colorama
Dynamic: author
Dynamic: description
Dynamic: description-content-type
Dynamic: requires-dist
Dynamic: requires-python
Dynamic: summary
